pyctftools/__init__.py
pyctftools/classiccrypto.py
pyctftools/letter_frequencies.py
pyctftools-0.0.1.dev2.dist-info/METADATA
pyctftools-0.0.1.dev2.dist-info/WHEEL
pyctftools-0.0.1.dev2.dist-info/licenses/LICENSE
pyctftools-0.0.1.dev2.dist-info/RECORD
