Metadata-Version: 2.4
Name: pyctftools
Version: 0.0.1.dev2
Summary: A python package containing my personal collection of scripts written over the years during CTF challanges.
Project-URL: Homepage, https://github.com/karstenroelofs/pyctftools
Project-URL: Issues, https://github.com/karstenroelofs/pyctftools/issues
Author-email: Karsten Roelofs <karsteneroelofs@gmail.com>
License-Expression: MIT
License-File: LICENSE
Requires-Python: >=3.9
Requires-Dist: english-words
Requires-Dist: tqdm
